dweather_client/__init__.py
dweather_client/aliases_and_units.py
dweather_client/client.py
dweather_client/df_loader.py
dweather_client/df_utils.py
dweather_client/grid_utils.py
dweather_client/http_queries.py
dweather_client/ipfs_errors.py
dweather_client/ipfs_queries.py
dweather_client/struct_utils.py
dweather_client/timeseries_utils.py
dweather_client/etc/airport-codes.csv
dweather_client/etc/bad_stations
dweather_client/etc/cpc-grid-ids.csv
dweather_client/etc/rtma_lat_lons.p.gz
dweather_client/tests/__init__.py
dweather_client/tests/test_aliases_and_units.py
dweather_client/tests/test_client.py
dweather_client/tests/test_df_loader.py
dweather_client/tests/test_grid_utils.py
dweather_client/tests/test_scripts.py
dweather_client/tests/test_timeseries_utils.py
dweather_client-2.1.0.dist-info/METADATA
dweather_client-2.1.0.dist-info/WHEEL
dweather_client-2.1.0.dist-info/top_level.txt
dweather_client-2.1.0.dist-info/RECORD
