Metadata-Version: 2.1
Name: dweather-client
Version: 2.1.0
Summary: Python client for interacting with weather data on IPFS.
Home-page: https://github.com/Arbol-Project/dWeather-Python-Client.git
Author: Arbol
Author-email: info@arbolmarket.com
License: UNKNOWN
Platform: UNKNOWN
Classifier: Programming Language :: Python :: 3
Classifier: License :: OSI Approved :: MIT License
Classifier: Operating System :: OS Independent
Requires-Python: >=3.6
Requires-Dist: ipfshttpclient (==0.6.1)
Requires-Dist: pandas (>=1.1.4)
Requires-Dist: pytest (>=6.1.2)
Requires-Dist: requests
Requires-Dist: geopy
Requires-Dist: zeep
Requires-Dist: astropy
Requires-Dist: timezonefinder
